methodlogger/__init__.py
methodlogger/decorators.py
methodlogger/log_config.py
methodlogger-0.1.2.dist-info/licenses/LICENSE
methodlogger-0.1.2.dist-info/METADATA
methodlogger-0.1.2.dist-info/WHEEL
methodlogger-0.1.2.dist-info/top_level.txt
methodlogger-0.1.2.dist-info/RECORD
