Metadata-Version: 2.4
Name: methodlogger
Version: 0.1.2
Summary: Log entry and exit of methods with a decorator
Author-email: Piyush Chauhan <piyush23321@gmail.com>
License: MIT
Keywords: logging,decorator,debug,trace
Requires-Python: >=3.7
License-File: LICENSE
Dynamic: license-file
